ai/backend/test/VERSION
ai/backend/test/__init__.py
ai/backend/test/py.typed
ai/backend/test/cli/__init__.py
ai/backend/test/cli/__main__.py
ai/backend/test/cli/context.py
ai/backend/test/cli/utils.py
ai/backend/test/cli_integration/__init__.py
ai/backend/test/cli_integration/conftest.py
ai/backend/test/cli_integration/admin/__init__.py
ai/backend/test/cli_integration/admin/test_domain.py
ai/backend/test/cli_integration/admin/test_group.py
ai/backend/test/cli_integration/admin/test_image.py
ai/backend/test/cli_integration/admin/test_keypair.py
ai/backend/test/cli_integration/admin/test_keypair_resource_policy.py
ai/backend/test/cli_integration/admin/test_scaling_group.py
ai/backend/test/cli_integration/admin/test_storage.py
ai/backend/test/cli_integration/admin/test_user.py
ai/backend/test/cli_integration/user/__init__.py
ai/backend/test/cli_integration/user/test_vfolder.py
ai/backend/test/contexts/__init__.py
ai/backend/test/contexts/auth.py
ai/backend/test/contexts/client_session.py
ai/backend/test/contexts/context.py
ai/backend/test/contexts/domain.py
ai/backend/test/contexts/group.py
ai/backend/test/contexts/image.py
ai/backend/test/contexts/model_service.py
ai/backend/test/contexts/resource_policy.py
ai/backend/test/contexts/scaling_group.py
ai/backend/test/contexts/session.py
ai/backend/test/contexts/sse.py
ai/backend/test/contexts/tester.py
ai/backend/test/contexts/user.py
ai/backend/test/contexts/vfolder.py
ai/backend/test/data/__init__.py
ai/backend/test/data/group.py
ai/backend/test/data/model_service.py
ai/backend/test/data/session.py
ai/backend/test/data/tester.py
ai/backend/test/data/user.py
ai/backend/test/data/vfolder.py
ai/backend/test/templates/__init__.py
ai/backend/test/templates/template.py
ai/backend/test/templates/auth/__init__.py
ai/backend/test/templates/auth/keypair.py
ai/backend/test/templates/auth/login.py
ai/backend/test/templates/group/__init__.py
ai/backend/test/templates/group/add_group_to_user.py
backend_ai_test-26.1.0.dist-info/METADATA
backend_ai_test-26.1.0.dist-info/WHEEL
backend_ai_test-26.1.0.dist-info/entry_points.txt
backend_ai_test-26.1.0.dist-info/namespace_packages.txt
backend_ai_test-26.1.0.dist-info/top_level.txt
backend_ai_test-26.1.0.dist-info/RECORD
